[
    {
        "id_giocatore":1,
        "nome":"Federico Di Mingo",
        "gol_individuali":1,
        "gol_fatti_squadra":10,
        "gol_subiti_squadra":5,
        "partite_giocate":1,
        "partite_vinte":1,
        "partite_pareggiate":0,
        "partite_perse":0,
        "voto_pagella":7.0,
        "id_partita":1,
        "squadra":"Chiari"
    },
    {
        "id_giocatore":2,
        "nome":"Davide Selva",
        "gol_individuali":1,
        "gol_fatti_squadra":10,
        "gol_subiti_squadra":5,
        "partite_giocate":1,
        "partite_vinte":1,
        "partite_pareggiate":0,
        "partite_perse":0,
        "voto_pagella":7.0,
        "id_partita":1,
        "squadra":"Chiari"
    },
    {
        "id_giocatore":3,
        "nome":"Riccardo Vezzoli",
        "gol_individuali":1,
        "gol_fatti_squadra":10,
        "gol_subiti_squadra":5,
        "partite_giocate":1,
        "partite_vinte":1,
        "partite_pareggiate":0,
        "partite_perse":0,
        "voto_pagella":7.0,
        "id_partita":1,
        "squadra":"Chiari"
    },
    {
        "id_giocatore":4,
        "nome":"Stefano Fraioli",
        "gol_individuali":2,
        "gol_fatti_squadra":10,
        "gol_subiti_squadra":5,
        "partite_giocate":1,
        "partite_vinte":1,
        "partite_pareggiate":0,
        "partite_perse":0,
        "voto_pagella":7.5,
        "id_partita":1,
        "squadra":"Chiari"
    },
    {
        "id_giocatore":5,
        "nome":"Francesco Basile",
        "gol_individuali":5,
        "gol_fatti_squadra":10,
        "gol_subiti_squadra":5,
        "partite_giocate":1,
        "partite_vinte":1,
        "partite_pareggiate":0,
        "partite_perse":0,
        "voto_pagella":8.0,
        "id_partita":1,
        "squadra":"Chiari"
    },
    {
        "id_giocatore":6,
        "nome":"Luca Peveraro",
        "gol_individuali":0,
        "gol_fatti_squadra":5,
        "gol_subiti_squadra":10,
        "partite_giocate":1,
        "partite_vinte":0,
        "partite_pareggiate":0,
        "partite_perse":1,
        "voto_pagella":5.5,
        "id_partita":1,
        "squadra":"Scuri"
    },
    {
        "id_giocatore":7,
        "nome":"Francesco Ballerio",
        "gol_individuali":0,
        "gol_fatti_squadra":5,
        "gol_subiti_squadra":10,
        "partite_giocate":1,
        "partite_vinte":0,
        "partite_pareggiate":0,
        "partite_perse":1,
        "voto_pagella":5.5,
        "id_partita":1,
        "squadra":"Scuri"
    },
    {
        "id_giocatore":8,
        "nome":"Filippo Caroggio",
        "gol_individuali":2,
        "gol_fatti_squadra":5,
        "gol_subiti_squadra":10,
        "partite_giocate":1,
        "partite_vinte":0,
        "partite_pareggiate":0,
        "partite_perse":1,
        "voto_pagella":5.5,
        "id_partita":1,
        "squadra":"Scuri"
    },
    {
        "id_giocatore":9,
        "nome":"Simone Ciardulli",
        "gol_individuali":2,
        "gol_fatti_squadra":5,
        "gol_subiti_squadra":10,
        "partite_giocate":1,
        "partite_vinte":0,
        "partite_pareggiate":0,
        "partite_perse":1,
        "voto_pagella":5.5,
        "id_partita":1,
        "squadra":"Scuri"
    },
    {
        "id_giocatore":10,
        "nome":"Luca Calce",
        "gol_individuali":1,
        "gol_fatti_squadra":5,
        "gol_subiti_squadra":10,
        "partite_giocate":1,
        "partite_vinte":0,
        "partite_pareggiate":0,
        "partite_perse":1,
        "voto_pagella":5.0,
        "id_partita":1,
        "squadra":"Scuri"
    },
    {
        "id_giocatore":11,
        "nome":"Riccardo Vezzoli",
        "gol_individuali":0,
        "gol_fatti_squadra":4,
        "gol_subiti_squadra":7,
        "partite_giocate":1,
        "partite_vinte":0,
        "partite_pareggiate":0,
        "partite_perse":1,
        "voto_pagella":5.5,
        "id_partita":2,
        "squadra":"Chiari"
    },
    {
        "id_giocatore":12,
        "nome":"Francesco Basile",
        "gol_individuali":1,
        "gol_fatti_squadra":4,
        "gol_subiti_squadra":7,
        "partite_giocate":1,
        "partite_vinte":0,
        "partite_pareggiate":0,
        "partite_perse":1,
        "voto_pagella":5.5,
        "id_partita":2,
        "squadra":"Chiari"
    },
    {
        "id_giocatore":13,
        "nome":"Stefano Charabou",
        "gol_individuali":1,
        "gol_fatti_squadra":4,
        "gol_subiti_squadra":7,
        "partite_giocate":1,
        "partite_vinte":0,
        "partite_pareggiate":0,
        "partite_perse":1,
        "voto_pagella":6.0,
        "id_partita":2,
        "squadra":"Chiari"
    },
    {
        "id_giocatore":14,
        "nome":"Matteo Nardone",
        "gol_individuali":0,
        "gol_fatti_squadra":4,
        "gol_subiti_squadra":7,
        "partite_giocate":1,
        "partite_vinte":0,
        "partite_pareggiate":0,
        "partite_perse":1,
        "voto_pagella":6.0,
        "id_partita":2,
        "squadra":"Chiari"
    },
    {
        "id_giocatore":15,
        "nome":"Federico Di Mingo",
        "gol_individuali":2,
        "gol_fatti_squadra":4,
        "gol_subiti_squadra":7,
        "partite_giocate":1,
        "partite_vinte":0,
        "partite_pareggiate":0,
        "partite_perse":1,
        "voto_pagella":6.0,
        "id_partita":2,
        "squadra":"Chiari"
    },
    {
        "id_giocatore":16,
        "nome":"Luca Peveraro",
        "gol_individuali":1,
        "gol_fatti_squadra":7,
        "gol_subiti_squadra":4,
        "partite_giocate":1,
        "partite_vinte":1,
        "partite_pareggiate":0,
        "partite_perse":0,
        "voto_pagella":6.5,
        "id_partita":2,
        "squadra":"Scuri"
    },
    {
        "id_giocatore":17,
        "nome":"Max Botta",
        "gol_individuali":0,
        "gol_fatti_squadra":7,
        "gol_subiti_squadra":4,
        "partite_giocate":1,
        "partite_vinte":1,
        "partite_pareggiate":0,
        "partite_perse":0,
        "voto_pagella":6.0,
        "id_partita":2,
        "squadra":"Scuri"
    },
    {
        "id_giocatore":18,
        "nome":"Davide Selva",
        "gol_individuali":1,
        "gol_fatti_squadra":7,
        "gol_subiti_squadra":4,
        "partite_giocate":1,
        "partite_vinte":1,
        "partite_pareggiate":0,
        "partite_perse":0,
        "voto_pagella":6.5,
        "id_partita":2,
        "squadra":"Scuri"
    },
    {
        "id_giocatore":19,
        "nome":"Simone Ciardulli",
        "gol_individuali":2,
        "gol_fatti_squadra":7,
        "gol_subiti_squadra":4,
        "partite_giocate":1,
        "partite_vinte":1,
        "partite_pareggiate":0,
        "partite_perse":0,
        "voto_pagella":6.5,
        "id_partita":2,
        "squadra":"Scuri"
    },
    {
        "id_giocatore":20,
        "nome":"Andrea Troletti",
        "gol_individuali":2,
        "gol_fatti_squadra":7,
        "gol_subiti_squadra":4,
        "partite_giocate":1,
        "partite_vinte":1,
        "partite_pareggiate":0,
        "partite_perse":0,
        "voto_pagella":6.5,
        "id_partita":2,
        "squadra":"Scuri"
    },
    {
        "id_giocatore":21,
        "nome":"Yonnis",
        "gol_individuali":3,
        "gol_fatti_squadra":7,
        "gol_subiti_squadra":9,
        "partite_giocate":1,
        "partite_vinte":0,
        "partite_pareggiate":0,
        "partite_perse":1,
        "voto_pagella":7.0,
        "id_partita":3,
        "squadra":"Chiari"
    },
    {
        "id_giocatore":22,
        "nome":"Luca Peveraro",
        "gol_individuali":3,
        "gol_fatti_squadra":7,
        "gol_subiti_squadra":9,
        "partite_giocate":1,
        "partite_vinte":0,
        "partite_pareggiate":0,
        "partite_perse":1,
        "voto_pagella":6.5,
        "id_partita":3,
        "squadra":"Chiari"
    },
    {
        "id_giocatore":23,
        "nome":"Luca Calce",
        "gol_individuali":0,
        "gol_fatti_squadra":7,
        "gol_subiti_squadra":9,
        "partite_giocate":1,
        "partite_vinte":0,
        "partite_pareggiate":0,
        "partite_perse":1,
        "voto_pagella":5.5,
        "id_partita":3,
        "squadra":"Chiari"
    },
    {
        "id_giocatore":24,
        "nome":"Stefano Charabou",
        "gol_individuali":0,
        "gol_fatti_squadra":7,
        "gol_subiti_squadra":9,
        "partite_giocate":1,
        "partite_vinte":0,
        "partite_pareggiate":0,
        "partite_perse":1,
        "voto_pagella":6.0,
        "id_partita":3,
        "squadra":"Chiari"
    },
    {
        "id_giocatore":25,
        "nome":"Andrea Troletti",
        "gol_individuali":1,
        "gol_fatti_squadra":7,
        "gol_subiti_squadra":9,
        "partite_giocate":1,
        "partite_vinte":0,
        "partite_pareggiate":0,
        "partite_perse":1,
        "voto_pagella":6.0,
        "id_partita":3,
        "squadra":"Chiari"
    },
    {
        "id_giocatore":26,
        "nome":"Federico Di Mingo",
        "gol_individuali":4,
        "gol_fatti_squadra":9,
        "gol_subiti_squadra":7,
        "partite_giocate":1,
        "partite_vinte":1,
        "partite_pareggiate":0,
        "partite_perse":0,
        "voto_pagella":7.5,
        "id_partita":3,
        "squadra":"Scuri"
    },
    {
        "id_giocatore":27,
        "nome":"Matteo Nardone",
        "gol_individuali":0,
        "gol_fatti_squadra":9,
        "gol_subiti_squadra":7,
        "partite_giocate":1,
        "partite_vinte":1,
        "partite_pareggiate":0,
        "partite_perse":0,
        "voto_pagella":6.0,
        "id_partita":3,
        "squadra":"Scuri"
    },
    {
        "id_giocatore":28,
        "nome":"Riccardo Vezzoli",
        "gol_individuali":1,
        "gol_fatti_squadra":9,
        "gol_subiti_squadra":7,
        "partite_giocate":1,
        "partite_vinte":1,
        "partite_pareggiate":0,
        "partite_perse":0,
        "voto_pagella":6.0,
        "id_partita":3,
        "squadra":"Scuri"
    },
    {
        "id_giocatore":29,
        "nome":"Max Botta",
        "gol_individuali":0,
        "gol_fatti_squadra":9,
        "gol_subiti_squadra":7,
        "partite_giocate":1,
        "partite_vinte":1,
        "partite_pareggiate":0,
        "partite_perse":0,
        "voto_pagella":6.0,
        "id_partita":3,
        "squadra":"Scuri"
    },
    {
        "id_giocatore":30,
        "nome":"Davide Selva",
        "gol_individuali":4,
        "gol_fatti_squadra":9,
        "gol_subiti_squadra":7,
        "partite_giocate":1,
        "partite_vinte":1,
        "partite_pareggiate":0,
        "partite_perse":0,
        "voto_pagella":7.0,
        "id_partita":3,
        "squadra":"Scuri"
    },
    {
        "id_giocatore":31,
        "nome":"Alberto Baretta",
        "gol_individuali":1,
        "gol_fatti_squadra":3,
        "gol_subiti_squadra":3,
        "partite_giocate":1,
        "partite_vinte":0,
        "partite_pareggiate":1,
        "partite_perse":0,
        "voto_pagella":6.5,
        "id_partita":4,
        "squadra":"Chiari"
    },
    {
        "id_giocatore":32,
        "nome":"Stefano Charabou",
        "gol_individuali":2,
        "gol_fatti_squadra":3,
        "gol_subiti_squadra":3,
        "partite_giocate":1,
        "partite_vinte":0,
        "partite_pareggiate":1,
        "partite_perse":0,
        "voto_pagella":7.0,
        "id_partita":4,
        "squadra":"Chiari"
    },
    {
        "id_giocatore":33,
        "nome":"Max Felicitas",
        "gol_individuali":0,
        "gol_fatti_squadra":3,
        "gol_subiti_squadra":3,
        "partite_giocate":1,
        "partite_vinte":0,
        "partite_pareggiate":1,
        "partite_perse":0,
        "voto_pagella":8.0,
        "id_partita":4,
        "squadra":"Chiari"
    },
    {
        "id_giocatore":34,
        "nome":"Luca Peveraro",
        "gol_individuali":0,
        "gol_fatti_squadra":3,
        "gol_subiti_squadra":3,
        "partite_giocate":1,
        "partite_vinte":0,
        "partite_pareggiate":1,
        "partite_perse":0,
        "voto_pagella":5.5,
        "id_partita":4,
        "squadra":"Chiari"
    },
    {
        "id_giocatore":35,
        "nome":"Francesco Basile",
        "gol_individuali":0,
        "gol_fatti_squadra":3,
        "gol_subiti_squadra":3,
        "partite_giocate":1,
        "partite_vinte":0,
        "partite_pareggiate":1,
        "partite_perse":0,
        "voto_pagella":5.5,
        "id_partita":4,
        "squadra":"Chiari"
    },
    {
        "id_giocatore":36,
        "nome":"Michele Marzulli",
        "gol_individuali":0,
        "gol_fatti_squadra":3,
        "gol_subiti_squadra":3,
        "partite_giocate":1,
        "partite_vinte":0,
        "partite_pareggiate":1,
        "partite_perse":0,
        "voto_pagella":6.5,
        "id_partita":4,
        "squadra":"Chiari"
    },
    {
        "id_giocatore":37,
        "nome":"Federico Di Mingo",
        "gol_individuali":2,
        "gol_fatti_squadra":3,
        "gol_subiti_squadra":3,
        "partite_giocate":1,
        "partite_vinte":0,
        "partite_pareggiate":1,
        "partite_perse":0,
        "voto_pagella":6.5,
        "id_partita":4,
        "squadra":"Scuri"
    },
    {
        "id_giocatore":38,
        "nome":"Giorgio Pedrazzini",
        "gol_individuali":1,
        "gol_fatti_squadra":3,
        "gol_subiti_squadra":3,
        "partite_giocate":1,
        "partite_vinte":0,
        "partite_pareggiate":1,
        "partite_perse":0,
        "voto_pagella":6.5,
        "id_partita":4,
        "squadra":"Scuri"
    },
    {
        "id_giocatore":39,
        "nome":"Giovanni Pedrazzini",
        "gol_individuali":0,
        "gol_fatti_squadra":3,
        "gol_subiti_squadra":3,
        "partite_giocate":1,
        "partite_vinte":0,
        "partite_pareggiate":1,
        "partite_perse":0,
        "voto_pagella":6.0,
        "id_partita":4,
        "squadra":"Scuri"
    },
    {
        "id_giocatore":40,
        "nome":"Davide Selva",
        "gol_individuali":0,
        "gol_fatti_squadra":3,
        "gol_subiti_squadra":3,
        "partite_giocate":1,
        "partite_vinte":0,
        "partite_pareggiate":1,
        "partite_perse":0,
        "voto_pagella":6.0,
        "id_partita":4,
        "squadra":"Scuri"
    },
    {
        "id_giocatore":41,
        "nome":"Matteo Nardone",
        "gol_individuali":0,
        "gol_fatti_squadra":3,
        "gol_subiti_squadra":3,
        "partite_giocate":1,
        "partite_vinte":0,
        "partite_pareggiate":1,
        "partite_perse":0,
        "voto_pagella":5.5,
        "id_partita":4,
        "squadra":"Scuri"
    },
    {
        "id_giocatore":42,
        "nome":"Andrea Troletti",
        "gol_individuali":0,
        "gol_fatti_squadra":3,
        "gol_subiti_squadra":3,
        "partite_giocate":1,
        "partite_vinte":0,
        "partite_pareggiate":1,
        "partite_perse":0,
        "voto_pagella":5.5,
        "id_partita":4,
        "squadra":"Scuri"
    },
    {
        "id_giocatore":43,
        "nome":"Luca Calce",
        "gol_individuali":2,
        "gol_fatti_squadra":7,
        "gol_subiti_squadra":9,
        "partite_giocate":1,
        "partite_vinte":0,
        "partite_pareggiate":0,
        "partite_perse":1,
        "voto_pagella":5.0,
        "id_partita":5,
        "squadra":"Chiari"
    },
    {
        "id_giocatore":44,
        "nome":"Luca Peveraro",
        "gol_individuali":1,
        "gol_fatti_squadra":7,
        "gol_subiti_squadra":9,
        "partite_giocate":1,
        "partite_vinte":0,
        "partite_pareggiate":0,
        "partite_perse":1,
        "voto_pagella":5.5,
        "id_partita":5,
        "squadra":"Chiari"
    },
    {
        "id_giocatore":45,
        "nome":"Federico Di Mingo",
        "gol_individuali":2,
        "gol_fatti_squadra":7,
        "gol_subiti_squadra":9,
        "partite_giocate":1,
        "partite_vinte":0,
        "partite_pareggiate":0,
        "partite_perse":1,
        "voto_pagella":6.0,
        "id_partita":5,
        "squadra":"Chiari"
    },
    {
        "id_giocatore":46,
        "nome":"Andrea Troletti",
        "gol_individuali":2,
        "gol_fatti_squadra":7,
        "gol_subiti_squadra":9,
        "partite_giocate":1,
        "partite_vinte":0,
        "partite_pareggiate":0,
        "partite_perse":1,
        "voto_pagella":5.5,
        "id_partita":5,
        "squadra":"Chiari"
    },
    {
        "id_giocatore":47,
        "nome":"Francesco Basile",
        "gol_individuali":0,
        "gol_fatti_squadra":7,
        "gol_subiti_squadra":9,
        "partite_giocate":1,
        "partite_vinte":0,
        "partite_pareggiate":0,
        "partite_perse":1,
        "voto_pagella":5.0,
        "id_partita":5,
        "squadra":"Chiari"
    },
    {
        "id_giocatore":48,
        "nome":"Riccardo Vezzoli",
        "gol_individuali":1,
        "gol_fatti_squadra":9,
        "gol_subiti_squadra":7,
        "partite_giocate":1,
        "partite_vinte":1,
        "partite_pareggiate":0,
        "partite_perse":0,
        "voto_pagella":7.0,
        "id_partita":5,
        "squadra":"Scuri"
    },
    {
        "id_giocatore":49,
        "nome":"Andrea Salvetti",
        "gol_individuali":2,
        "gol_fatti_squadra":9,
        "gol_subiti_squadra":7,
        "partite_giocate":1,
        "partite_vinte":1,
        "partite_pareggiate":0,
        "partite_perse":0,
        "voto_pagella":7.5,
        "id_partita":5,
        "squadra":"Scuri"
    },
    {
        "id_giocatore":50,
        "nome":"Max Botta",
        "gol_individuali":1,
        "gol_fatti_squadra":9,
        "gol_subiti_squadra":7,
        "partite_giocate":1,
        "partite_vinte":1,
        "partite_pareggiate":0,
        "partite_perse":0,
        "voto_pagella":6.0,
        "id_partita":5,
        "squadra":"Scuri"
    },
    {
        "id_giocatore":51,
        "nome":"Angelo Bott",
        "gol_individuali":1,
        "gol_fatti_squadra":9,
        "gol_subiti_squadra":7,
        "partite_giocate":1,
        "partite_vinte":1,
        "partite_pareggiate":0,
        "partite_perse":0,
        "voto_pagella":6.0,
        "id_partita":5,
        "squadra":"Scuri"
    },
    {
        "id_giocatore":52,
        "nome":"Marco Bott",
        "gol_individuali":4,
        "gol_fatti_squadra":9,
        "gol_subiti_squadra":7,
        "partite_giocate":1,
        "partite_vinte":1,
        "partite_pareggiate":0,
        "partite_perse":0,
        "voto_pagella":6.5,
        "id_partita":5,
        "squadra":"Scuri"
    },
    {
        "id_giocatore":53,
        "nome":"Riccardo Vezzoli",
        "gol_individuali":0,
        "gol_fatti_squadra":10,
        "gol_subiti_squadra":10,
        "partite_giocate":1,
        "partite_vinte":0,
        "partite_pareggiate":1,
        "partite_perse":0,
        "voto_pagella":6.0,
        "id_partita":6,
        "squadra":"Chiari"
    },
    {
        "id_giocatore":54,
        "nome":"Simone Ciardulli",
        "gol_individuali":4,
        "gol_fatti_squadra":10,
        "gol_subiti_squadra":10,
        "partite_giocate":1,
        "partite_vinte":0,
        "partite_pareggiate":1,
        "partite_perse":0,
        "voto_pagella":7.0,
        "id_partita":6,
        "squadra":"Chiari"
    },
    {
        "id_giocatore":55,
        "nome":"Davide Selva",
        "gol_individuali":4,
        "gol_fatti_squadra":10,
        "gol_subiti_squadra":10,
        "partite_giocate":1,
        "partite_vinte":0,
        "partite_pareggiate":1,
        "partite_perse":0,
        "voto_pagella":6.5,
        "id_partita":6,
        "squadra":"Chiari"
    },
    {
        "id_giocatore":56,
        "nome":"Francesco Basile",
        "gol_individuali":0,
        "gol_fatti_squadra":10,
        "gol_subiti_squadra":10,
        "partite_giocate":1,
        "partite_vinte":0,
        "partite_pareggiate":1,
        "partite_perse":0,
        "voto_pagella":5.0,
        "id_partita":6,
        "squadra":"Chiari"
    },
    {
        "id_giocatore":57,
        "nome":"Max Botta",
        "gol_individuali":2,
        "gol_fatti_squadra":10,
        "gol_subiti_squadra":10,
        "partite_giocate":1,
        "partite_vinte":0,
        "partite_pareggiate":1,
        "partite_perse":0,
        "voto_pagella":6.0,
        "id_partita":6,
        "squadra":"Chiari"
    },
    {
        "id_giocatore":58,
        "nome":"Federico Di Mingo",
        "gol_individuali":1,
        "gol_fatti_squadra":10,
        "gol_subiti_squadra":10,
        "partite_giocate":1,
        "partite_vinte":0,
        "partite_pareggiate":1,
        "partite_perse":0,
        "voto_pagella":6.0,
        "id_partita":6,
        "squadra":"Scuri"
    },
    {
        "id_giocatore":59,
        "nome":"Matteo Nardone",
        "gol_individuali":0,
        "gol_fatti_squadra":10,
        "gol_subiti_squadra":10,
        "partite_giocate":1,
        "partite_vinte":0,
        "partite_pareggiate":1,
        "partite_perse":0,
        "voto_pagella":6.0,
        "id_partita":6,
        "squadra":"Scuri"
    },
    {
        "id_giocatore":60,
        "nome":"Andrea Troletti",
        "gol_individuali":6,
        "gol_fatti_squadra":10,
        "gol_subiti_squadra":10,
        "partite_giocate":1,
        "partite_vinte":0,
        "partite_pareggiate":1,
        "partite_perse":0,
        "voto_pagella":8.0,
        "id_partita":6,
        "squadra":"Scuri"
    },
    {
        "id_giocatore":61,
        "nome":"Diego Franzosi",
        "gol_individuali":2,
        "gol_fatti_squadra":10,
        "gol_subiti_squadra":10,
        "partite_giocate":1,
        "partite_vinte":0,
        "partite_pareggiate":1,
        "partite_perse":0,
        "voto_pagella":6.5,
        "id_partita":6,
        "squadra":"Scuri"
    },
    {
        "id_giocatore":62,
        "nome":"Giovanni Pedrazzini",
        "gol_individuali":1,
        "gol_fatti_squadra":10,
        "gol_subiti_squadra":10,
        "partite_giocate":1,
        "partite_vinte":0,
        "partite_pareggiate":1,
        "partite_perse":0,
        "voto_pagella":6.0,
        "id_partita":6,
        "squadra":"Scuri"
    },
    {
        "id_giocatore":63,
        "nome":"Alberto Baretta",
        "gol_individuali":2,
        "gol_fatti_squadra":8,
        "gol_subiti_squadra":7,
        "partite_giocate":1,
        "partite_vinte":1,
        "partite_pareggiate":0,
        "partite_perse":0,
        "voto_pagella":7.0,
        "id_partita":7,
        "squadra":"Chiari"
    },
    {
        "id_giocatore":64,
        "nome":"Stefano Charabou",
        "gol_individuali":3,
        "gol_fatti_squadra":8,
        "gol_subiti_squadra":7,
        "partite_giocate":1,
        "partite_vinte":1,
        "partite_pareggiate":0,
        "partite_perse":0,
        "voto_pagella":7.0,
        "id_partita":7,
        "squadra":"Chiari"
    },
    {
        "id_giocatore":65,
        "nome":"Matteo Nardone",
        "gol_individuali":0,
        "gol_fatti_squadra":8,
        "gol_subiti_squadra":7,
        "partite_giocate":1,
        "partite_vinte":1,
        "partite_pareggiate":0,
        "partite_perse":0,
        "voto_pagella":6.0,
        "id_partita":7,
        "squadra":"Chiari"
    },
    {
        "id_giocatore":66,
        "nome":"Giovanni Pedrazzini",
        "gol_individuali":3,
        "gol_fatti_squadra":8,
        "gol_subiti_squadra":7,
        "partite_giocate":1,
        "partite_vinte":1,
        "partite_pareggiate":0,
        "partite_perse":0,
        "voto_pagella":7.0,
        "id_partita":7,
        "squadra":"Chiari"
    },
    {
        "id_giocatore":67,
        "nome":"Nosenzo Junior",
        "gol_individuali":0,
        "gol_fatti_squadra":8,
        "gol_subiti_squadra":7,
        "partite_giocate":1,
        "partite_vinte":1,
        "partite_pareggiate":0,
        "partite_perse":0,
        "voto_pagella":6.0,
        "id_partita":7,
        "squadra":"Chiari"
    },
    {
        "id_giocatore":68,
        "nome":"Luca Calce",
        "gol_individuali":0,
        "gol_fatti_squadra":7,
        "gol_subiti_squadra":8,
        "partite_giocate":1,
        "partite_vinte":0,
        "partite_pareggiate":0,
        "partite_perse":1,
        "voto_pagella":5.5,
        "id_partita":7,
        "squadra":"Scuri"
    },
    {
        "id_giocatore":69,
        "nome":"Luca Peveraro",
        "gol_individuali":0,
        "gol_fatti_squadra":7,
        "gol_subiti_squadra":8,
        "partite_giocate":1,
        "partite_vinte":0,
        "partite_pareggiate":0,
        "partite_perse":1,
        "voto_pagella":6.0,
        "id_partita":7,
        "squadra":"Scuri"
    },
    {
        "id_giocatore":70,
        "nome":"Michele Marzulli",
        "gol_individuali":3,
        "gol_fatti_squadra":7,
        "gol_subiti_squadra":8,
        "partite_giocate":1,
        "partite_vinte":0,
        "partite_pareggiate":0,
        "partite_perse":1,
        "voto_pagella":6.5,
        "id_partita":7,
        "squadra":"Scuri"
    },
    {
        "id_giocatore":71,
        "nome":"Davide Selva",
        "gol_individuali":2,
        "gol_fatti_squadra":7,
        "gol_subiti_squadra":8,
        "partite_giocate":1,
        "partite_vinte":0,
        "partite_pareggiate":0,
        "partite_perse":1,
        "voto_pagella":6.0,
        "id_partita":7,
        "squadra":"Scuri"
    },
    {
        "id_giocatore":72,
        "nome":"Federico Di Mingo",
        "gol_individuali":2,
        "gol_fatti_squadra":7,
        "gol_subiti_squadra":8,
        "partite_giocate":1,
        "partite_vinte":0,
        "partite_pareggiate":0,
        "partite_perse":1,
        "voto_pagella":6.0,
        "id_partita":7,
        "squadra":"Scuri"
    },
    {
        "id_giocatore":73,
        "nome":"Davide Selva",
        "gol_individuali":5,
        "gol_fatti_squadra":11,
        "gol_subiti_squadra":8,
        "partite_giocate":1,
        "partite_vinte":1,
        "partite_pareggiate":0,
        "partite_perse":0,
        "voto_pagella":7.5,
        "id_partita":8,
        "squadra":"Chiari"
    },
    {
        "id_giocatore":74,
        "nome":"Giovanni Pedrazzini",
        "gol_individuali":3,
        "gol_fatti_squadra":11,
        "gol_subiti_squadra":8,
        "partite_giocate":1,
        "partite_vinte":1,
        "partite_pareggiate":0,
        "partite_perse":0,
        "voto_pagella":7.0,
        "id_partita":8,
        "squadra":"Chiari"
    },
    {
        "id_giocatore":75,
        "nome":"Stefano Charabou",
        "gol_individuali":1,
        "gol_fatti_squadra":11,
        "gol_subiti_squadra":8,
        "partite_giocate":1,
        "partite_vinte":1,
        "partite_pareggiate":0,
        "partite_perse":0,
        "voto_pagella":6.5,
        "id_partita":8,
        "squadra":"Chiari"
    },
    {
        "id_giocatore":76,
        "nome":"Claudio Di Ruscio",
        "gol_individuali":0,
        "gol_fatti_squadra":11,
        "gol_subiti_squadra":8,
        "partite_giocate":1,
        "partite_vinte":1,
        "partite_pareggiate":0,
        "partite_perse":0,
        "voto_pagella":5.5,
        "id_partita":8,
        "squadra":"Chiari"
    },
    {
        "id_giocatore":77,
        "nome":"Max Botta",
        "gol_individuali":1,
        "gol_fatti_squadra":11,
        "gol_subiti_squadra":8,
        "partite_giocate":1,
        "partite_vinte":1,
        "partite_pareggiate":0,
        "partite_perse":0,
        "voto_pagella":6.0,
        "id_partita":8,
        "squadra":"Chiari"
    },
    {
        "id_giocatore":78,
        "nome":"Federico Di Mingo",
        "gol_individuali":1,
        "gol_fatti_squadra":8,
        "gol_subiti_squadra":11,
        "partite_giocate":1,
        "partite_vinte":0,
        "partite_pareggiate":0,
        "partite_perse":1,
        "voto_pagella":5.5,
        "id_partita":8,
        "squadra":"Scuri"
    },
    {
        "id_giocatore":79,
        "nome":"Andrea Troletti",
        "gol_individuali":3,
        "gol_fatti_squadra":8,
        "gol_subiti_squadra":11,
        "partite_giocate":1,
        "partite_vinte":0,
        "partite_pareggiate":0,
        "partite_perse":1,
        "voto_pagella":6.5,
        "id_partita":8,
        "squadra":"Scuri"
    },
    {
        "id_giocatore":80,
        "nome":"Matteo Nardone",
        "gol_individuali":2,
        "gol_fatti_squadra":8,
        "gol_subiti_squadra":11,
        "partite_giocate":1,
        "partite_vinte":0,
        "partite_pareggiate":0,
        "partite_perse":1,
        "voto_pagella":5.5,
        "id_partita":8,
        "squadra":"Scuri"
    },
    {
        "id_giocatore":81,
        "nome":"Diego Franzosi",
        "gol_individuali":2,
        "gol_fatti_squadra":8,
        "gol_subiti_squadra":11,
        "partite_giocate":1,
        "partite_vinte":0,
        "partite_pareggiate":0,
        "partite_perse":1,
        "voto_pagella":6.0,
        "id_partita":8,
        "squadra":"Scuri"
    },
    {
        "id_giocatore":82,
        "nome":"Riccardo Vezzoli",
        "gol_individuali":0,
        "gol_fatti_squadra":8,
        "gol_subiti_squadra":11,
        "partite_giocate":1,
        "partite_vinte":0,
        "partite_pareggiate":0,
        "partite_perse":1,
        "voto_pagella":5.5,
        "id_partita":8,
        "squadra":"Scuri"
    },
    {
        "id_giocatore":83,
        "nome":"Riccardo Vezzoli",
        "gol_individuali":2,
        "gol_fatti_squadra":8,
        "gol_subiti_squadra":7,
        "partite_giocate":1,
        "partite_vinte":1,
        "partite_pareggiate":0,
        "partite_perse":0,
        "voto_pagella":6.5,
        "id_partita":9,
        "squadra":"Chiari"
    },
    {
        "id_giocatore":84,
        "nome":"Luca Peveraro",
        "gol_individuali":2,
        "gol_fatti_squadra":8,
        "gol_subiti_squadra":7,
        "partite_giocate":1,
        "partite_vinte":1,
        "partite_pareggiate":0,
        "partite_perse":0,
        "voto_pagella":7.0,
        "id_partita":9,
        "squadra":"Chiari"
    },
    {
        "id_giocatore":85,
        "nome":"Francesco Basile",
        "gol_individuali":2,
        "gol_fatti_squadra":8,
        "gol_subiti_squadra":7,
        "partite_giocate":1,
        "partite_vinte":1,
        "partite_pareggiate":0,
        "partite_perse":0,
        "voto_pagella":6.0,
        "id_partita":9,
        "squadra":"Chiari"
    },
    {
        "id_giocatore":86,
        "nome":"Max Botta",
        "gol_individuali":1,
        "gol_fatti_squadra":8,
        "gol_subiti_squadra":7,
        "partite_giocate":1,
        "partite_vinte":1,
        "partite_pareggiate":0,
        "partite_perse":0,
        "voto_pagella":6.5,
        "id_partita":9,
        "squadra":"Chiari"
    },
    {
        "id_giocatore":87,
        "nome":"Maik",
        "gol_individuali":1,
        "gol_fatti_squadra":8,
        "gol_subiti_squadra":7,
        "partite_giocate":1,
        "partite_vinte":1,
        "partite_pareggiate":0,
        "partite_perse":0,
        "voto_pagella":7.5,
        "id_partita":9,
        "squadra":"Chiari"
    },
    {
        "id_giocatore":88,
        "nome":"Luca Calce",
        "gol_individuali":1,
        "gol_fatti_squadra":7,
        "gol_subiti_squadra":8,
        "partite_giocate":1,
        "partite_vinte":0,
        "partite_pareggiate":0,
        "partite_perse":1,
        "voto_pagella":6.0,
        "id_partita":9,
        "squadra":"Scuri"
    },
    {
        "id_giocatore":89,
        "nome":"Federico Di Mingo",
        "gol_individuali":3,
        "gol_fatti_squadra":7,
        "gol_subiti_squadra":8,
        "partite_giocate":1,
        "partite_vinte":0,
        "partite_pareggiate":0,
        "partite_perse":1,
        "voto_pagella":6.5,
        "id_partita":9,
        "squadra":"Scuri"
    },
    {
        "id_giocatore":90,
        "nome":"Filippo Caroggio",
        "gol_individuali":1,
        "gol_fatti_squadra":7,
        "gol_subiti_squadra":8,
        "partite_giocate":1,
        "partite_vinte":0,
        "partite_pareggiate":0,
        "partite_perse":1,
        "voto_pagella":6.0,
        "id_partita":9,
        "squadra":"Scuri"
    },
    {
        "id_giocatore":91,
        "nome":"Andrea Troletti",
        "gol_individuali":2,
        "gol_fatti_squadra":7,
        "gol_subiti_squadra":8,
        "partite_giocate":1,
        "partite_vinte":0,
        "partite_pareggiate":0,
        "partite_perse":1,
        "voto_pagella":6.5,
        "id_partita":9,
        "squadra":"Scuri"
    },
    {
        "id_giocatore":92,
        "nome":"Taormina",
        "gol_individuali":0,
        "gol_fatti_squadra":7,
        "gol_subiti_squadra":8,
        "partite_giocate":1,
        "partite_vinte":0,
        "partite_pareggiate":0,
        "partite_perse":1,
        "voto_pagella":5.5,
        "id_partita":9,
        "squadra":"Scuri"
    },
    {
        "id_giocatore":93,
        "nome":"Nosenzo Senior",
        "gol_individuali":0,
        "gol_fatti_squadra":5,
        "gol_subiti_squadra":10,
        "partite_giocate":1,
        "partite_vinte":0,
        "partite_pareggiate":0,
        "partite_perse":1,
        "voto_pagella":5.5,
        "id_partita":10,
        "squadra":"Chiari"
    },
    {
        "id_giocatore":94,
        "nome":"Stefano Fumagalli",
        "gol_individuali":1,
        "gol_fatti_squadra":5,
        "gol_subiti_squadra":10,
        "partite_giocate":1,
        "partite_vinte":0,
        "partite_pareggiate":0,
        "partite_perse":1,
        "voto_pagella":6.0,
        "id_partita":10,
        "squadra":"Chiari"
    },
    {
        "id_giocatore":95,
        "nome":"Michele Marzulli",
        "gol_individuali":1,
        "gol_fatti_squadra":5,
        "gol_subiti_squadra":10,
        "partite_giocate":1,
        "partite_vinte":0,
        "partite_pareggiate":0,
        "partite_perse":1,
        "voto_pagella":5.5,
        "id_partita":10,
        "squadra":"Chiari"
    },
    {
        "id_giocatore":96,
        "nome":"Federico Di Mingo",
        "gol_individuali":0,
        "gol_fatti_squadra":5,
        "gol_subiti_squadra":10,
        "partite_giocate":1,
        "partite_vinte":0,
        "partite_pareggiate":0,
        "partite_perse":1,
        "voto_pagella":5.5,
        "id_partita":10,
        "squadra":"Chiari"
    },
    {
        "id_giocatore":97,
        "nome":"Matteo Nardone",
        "gol_individuali":1,
        "gol_fatti_squadra":5,
        "gol_subiti_squadra":10,
        "partite_giocate":1,
        "partite_vinte":0,
        "partite_pareggiate":0,
        "partite_perse":1,
        "voto_pagella":5.5,
        "id_partita":10,
        "squadra":"Chiari"
    },
    {
        "id_giocatore":98,
        "nome":"Andrea Troletti",
        "gol_individuali":3,
        "gol_fatti_squadra":10,
        "gol_subiti_squadra":5,
        "partite_giocate":1,
        "partite_vinte":1,
        "partite_pareggiate":0,
        "partite_perse":0,
        "voto_pagella":7.5,
        "id_partita":10,
        "squadra":"Scuri"
    },
    {
        "id_giocatore":99,
        "nome":"Davide Selva",
        "gol_individuali":2,
        "gol_fatti_squadra":10,
        "gol_subiti_squadra":5,
        "partite_giocate":1,
        "partite_vinte":1,
        "partite_pareggiate":0,
        "partite_perse":0,
        "voto_pagella":6.5,
        "id_partita":10,
        "squadra":"Scuri"
    },
    {
        "id_giocatore":100,
        "nome":"Luca Calce",
        "gol_individuali":3,
        "gol_fatti_squadra":10,
        "gol_subiti_squadra":5,
        "partite_giocate":1,
        "partite_vinte":1,
        "partite_pareggiate":0,
        "partite_perse":0,
        "voto_pagella":6.5,
        "id_partita":10,
        "squadra":"Scuri"
    },
    {
        "id_giocatore":101,
        "nome":"Max Botta",
        "gol_individuali":0,
        "gol_fatti_squadra":10,
        "gol_subiti_squadra":5,
        "partite_giocate":1,
        "partite_vinte":1,
        "partite_pareggiate":0,
        "partite_perse":0,
        "voto_pagella":6.0,
        "id_partita":10,
        "squadra":"Scuri"
    },
    {
        "id_giocatore":102,
        "nome":"Luca Peveraro",
        "gol_individuali":2,
        "gol_fatti_squadra":10,
        "gol_subiti_squadra":5,
        "partite_giocate":1,
        "partite_vinte":1,
        "partite_pareggiate":0,
        "partite_perse":0,
        "voto_pagella":6.5,
        "id_partita":10,
        "squadra":"Scuri"
    },
    {
        "id_giocatore":103,
        "nome":"Federico Di Mingo",
        "gol_individuali":1,
        "gol_fatti_squadra":11,
        "gol_subiti_squadra":8,
        "partite_giocate":1,
        "partite_vinte":1,
        "partite_pareggiate":0,
        "partite_perse":0,
        "voto_pagella":6.5,
        "id_partita":11,
        "squadra":"Chiari"
    },
    {
        "id_giocatore":104,
        "nome":"Luca Vazio",
        "gol_individuali":2,
        "gol_fatti_squadra":11,
        "gol_subiti_squadra":8,
        "partite_giocate":1,
        "partite_vinte":1,
        "partite_pareggiate":0,
        "partite_perse":0,
        "voto_pagella":6.5,
        "id_partita":11,
        "squadra":"Chiari"
    },
    {
        "id_giocatore":105,
        "nome":"Nicolas Carboni",
        "gol_individuali":3,
        "gol_fatti_squadra":11,
        "gol_subiti_squadra":8,
        "partite_giocate":1,
        "partite_vinte":1,
        "partite_pareggiate":0,
        "partite_perse":0,
        "voto_pagella":7.0,
        "id_partita":11,
        "squadra":"Chiari"
    },
    {
        "id_giocatore":106,
        "nome":"Andrea Troletti",
        "gol_individuali":2,
        "gol_fatti_squadra":11,
        "gol_subiti_squadra":8,
        "partite_giocate":1,
        "partite_vinte":1,
        "partite_pareggiate":0,
        "partite_perse":0,
        "voto_pagella":7.0,
        "id_partita":11,
        "squadra":"Chiari"
    },
    {
        "id_giocatore":107,
        "nome":"Davide Selva",
        "gol_individuali":2,
        "gol_fatti_squadra":11,
        "gol_subiti_squadra":8,
        "partite_giocate":1,
        "partite_vinte":1,
        "partite_pareggiate":0,
        "partite_perse":0,
        "voto_pagella":6.5,
        "id_partita":11,
        "squadra":"Chiari"
    },
    {
        "id_giocatore":108,
        "nome":"Luca Calce",
        "gol_individuali":2,
        "gol_fatti_squadra":8,
        "gol_subiti_squadra":11,
        "partite_giocate":1,
        "partite_vinte":0,
        "partite_pareggiate":0,
        "partite_perse":1,
        "voto_pagella":6.0,
        "id_partita":11,
        "squadra":"Scuri"
    },
    {
        "id_giocatore":109,
        "nome":"Francesco Basile",
        "gol_individuali":3,
        "gol_fatti_squadra":8,
        "gol_subiti_squadra":11,
        "partite_giocate":1,
        "partite_vinte":0,
        "partite_pareggiate":0,
        "partite_perse":1,
        "voto_pagella":6.0,
        "id_partita":11,
        "squadra":"Scuri"
    },
    {
        "id_giocatore":110,
        "nome":"Simone Ciardulli",
        "gol_individuali":2,
        "gol_fatti_squadra":8,
        "gol_subiti_squadra":11,
        "partite_giocate":1,
        "partite_vinte":0,
        "partite_pareggiate":0,
        "partite_perse":1,
        "voto_pagella":5.5,
        "id_partita":11,
        "squadra":"Scuri"
    },
    {
        "id_giocatore":111,
        "nome":"Luca Peveraro",
        "gol_individuali":0,
        "gol_fatti_squadra":8,
        "gol_subiti_squadra":11,
        "partite_giocate":1,
        "partite_vinte":0,
        "partite_pareggiate":0,
        "partite_perse":1,
        "voto_pagella":5.5,
        "id_partita":11,
        "squadra":"Scuri"
    },
    {
        "id_giocatore":112,
        "nome":"Michele Marzulli",
        "gol_individuali":1,
        "gol_fatti_squadra":8,
        "gol_subiti_squadra":11,
        "partite_giocate":1,
        "partite_vinte":0,
        "partite_pareggiate":0,
        "partite_perse":1,
        "voto_pagella":6.0,
        "id_partita":11,
        "squadra":"Scuri"
    },
    {
        "id_giocatore":113,
        "nome":"Davide Selva",
        "gol_individuali":0,
        "gol_fatti_squadra":9,
        "gol_subiti_squadra":7,
        "partite_giocate":1,
        "partite_vinte":1,
        "partite_pareggiate":0,
        "partite_perse":0,
        "voto_pagella":5.5,
        "id_partita":12,
        "squadra":"Chiari"
    },
    {
        "id_giocatore":114,
        "nome":"Federico Di Mingo",
        "gol_individuali":3,
        "gol_fatti_squadra":9,
        "gol_subiti_squadra":7,
        "partite_giocate":1,
        "partite_vinte":1,
        "partite_pareggiate":0,
        "partite_perse":0,
        "voto_pagella":6.5,
        "id_partita":12,
        "squadra":"Chiari"
    },
    {
        "id_giocatore":115,
        "nome":"Luca Peveraro",
        "gol_individuali":0,
        "gol_fatti_squadra":9,
        "gol_subiti_squadra":7,
        "partite_giocate":1,
        "partite_vinte":1,
        "partite_pareggiate":0,
        "partite_perse":0,
        "voto_pagella":6.0,
        "id_partita":12,
        "squadra":"Chiari"
    },
    {
        "id_giocatore":116,
        "nome":"Luca Calce",
        "gol_individuali":2,
        "gol_fatti_squadra":9,
        "gol_subiti_squadra":7,
        "partite_giocate":1,
        "partite_vinte":1,
        "partite_pareggiate":0,
        "partite_perse":0,
        "voto_pagella":6.0,
        "id_partita":12,
        "squadra":"Chiari"
    },
    {
        "id_giocatore":117,
        "nome":"Andrea Troletti",
        "gol_individuali":3,
        "gol_fatti_squadra":9,
        "gol_subiti_squadra":7,
        "partite_giocate":1,
        "partite_vinte":1,
        "partite_pareggiate":0,
        "partite_perse":0,
        "voto_pagella":7.0,
        "id_partita":12,
        "squadra":"Chiari"
    },
    {
        "id_giocatore":118,
        "nome":"Riccardo Vezzoli",
        "gol_individuali":3,
        "gol_fatti_squadra":7,
        "gol_subiti_squadra":9,
        "partite_giocate":1,
        "partite_vinte":0,
        "partite_pareggiate":0,
        "partite_perse":1,
        "voto_pagella":7.0,
        "id_partita":12,
        "squadra":"Scuri"
    },
    {
        "id_giocatore":119,
        "nome":"Cesare Bott",
        "gol_individuali":1,
        "gol_fatti_squadra":7,
        "gol_subiti_squadra":9,
        "partite_giocate":1,
        "partite_vinte":0,
        "partite_pareggiate":0,
        "partite_perse":1,
        "voto_pagella":6.5,
        "id_partita":12,
        "squadra":"Scuri"
    },
    {
        "id_giocatore":120,
        "nome":"Max Botta",
        "gol_individuali":1,
        "gol_fatti_squadra":7,
        "gol_subiti_squadra":9,
        "partite_giocate":1,
        "partite_vinte":0,
        "partite_pareggiate":0,
        "partite_perse":1,
        "voto_pagella":5.5,
        "id_partita":12,
        "squadra":"Scuri"
    },
    {
        "id_giocatore":121,
        "nome":"Matteo Nardone",
        "gol_individuali":1,
        "gol_fatti_squadra":7,
        "gol_subiti_squadra":9,
        "partite_giocate":1,
        "partite_vinte":0,
        "partite_pareggiate":0,
        "partite_perse":1,
        "voto_pagella":6.0,
        "id_partita":12,
        "squadra":"Scuri"
    },
    {
        "id_giocatore":122,
        "nome":"Simone Ciardulli",
        "gol_individuali":1,
        "gol_fatti_squadra":7,
        "gol_subiti_squadra":9,
        "partite_giocate":1,
        "partite_vinte":0,
        "partite_pareggiate":0,
        "partite_perse":1,
        "voto_pagella":6.0,
        "id_partita":12,
        "squadra":"Scuri"
    },
    {
        "id_giocatore":123,
        "nome":"Luca Calce",
        "gol_individuali":2,
        "gol_fatti_squadra":6,
        "gol_subiti_squadra":5,
        "partite_giocate":1,
        "partite_vinte":1,
        "partite_pareggiate":0,
        "partite_perse":0,
        "voto_pagella":6.5,
        "id_partita":13,
        "squadra":"Chiari"
    },
    {
        "id_giocatore":124,
        "nome":"Luca Peveraro",
        "gol_individuali":2,
        "gol_fatti_squadra":6,
        "gol_subiti_squadra":5,
        "partite_giocate":1,
        "partite_vinte":1,
        "partite_pareggiate":0,
        "partite_perse":0,
        "voto_pagella":6.5,
        "id_partita":13,
        "squadra":"Chiari"
    },
    {
        "id_giocatore":125,
        "nome":"Davide Selva",
        "gol_individuali":1,
        "gol_fatti_squadra":6,
        "gol_subiti_squadra":5,
        "partite_giocate":1,
        "partite_vinte":1,
        "partite_pareggiate":0,
        "partite_perse":0,
        "voto_pagella":6.0,
        "id_partita":13,
        "squadra":"Chiari"
    },
    {
        "id_giocatore":126,
        "nome":"Matteo Nardone",
        "gol_individuali":0,
        "gol_fatti_squadra":6,
        "gol_subiti_squadra":5,
        "partite_giocate":1,
        "partite_vinte":1,
        "partite_pareggiate":0,
        "partite_perse":0,
        "voto_pagella":6.0,
        "id_partita":13,
        "squadra":"Chiari"
    },
    {
        "id_giocatore":127,
        "nome":"Andrea Troletti",
        "gol_individuali":1,
        "gol_fatti_squadra":6,
        "gol_subiti_squadra":5,
        "partite_giocate":1,
        "partite_vinte":1,
        "partite_pareggiate":0,
        "partite_perse":0,
        "voto_pagella":6.0,
        "id_partita":13,
        "squadra":"Chiari"
    },
    {
        "id_giocatore":128,
        "nome":"Diego Capperucci",
        "gol_individuali":1,
        "gol_fatti_squadra":5,
        "gol_subiti_squadra":6,
        "partite_giocate":1,
        "partite_vinte":0,
        "partite_pareggiate":0,
        "partite_perse":1,
        "voto_pagella":6.5,
        "id_partita":13,
        "squadra":"Scuri"
    },
    {
        "id_giocatore":129,
        "nome":"Federico Di Mingo",
        "gol_individuali":1,
        "gol_fatti_squadra":5,
        "gol_subiti_squadra":6,
        "partite_giocate":1,
        "partite_vinte":0,
        "partite_pareggiate":0,
        "partite_perse":1,
        "voto_pagella":5.5,
        "id_partita":13,
        "squadra":"Scuri"
    },
    {
        "id_giocatore":130,
        "nome":"Francesco Basile",
        "gol_individuali":0,
        "gol_fatti_squadra":5,
        "gol_subiti_squadra":6,
        "partite_giocate":1,
        "partite_vinte":0,
        "partite_pareggiate":0,
        "partite_perse":1,
        "voto_pagella":5.5,
        "id_partita":13,
        "squadra":"Scuri"
    },
    {
        "id_giocatore":131,
        "nome":"Max Botta",
        "gol_individuali":2,
        "gol_fatti_squadra":5,
        "gol_subiti_squadra":6,
        "partite_giocate":1,
        "partite_vinte":0,
        "partite_pareggiate":0,
        "partite_perse":1,
        "voto_pagella":6.5,
        "id_partita":13,
        "squadra":"Scuri"
    },
    {
        "id_giocatore":132,
        "nome":"Riccardo Vezzoli",
        "gol_individuali":1,
        "gol_fatti_squadra":5,
        "gol_subiti_squadra":6,
        "partite_giocate":1,
        "partite_vinte":0,
        "partite_pareggiate":0,
        "partite_perse":1,
        "voto_pagella":6.0,
        "id_partita":13,
        "squadra":"Scuri"
    },
    {
        "id_giocatore":133,
        "nome":"Federico Di Mingo",
        "gol_individuali":4,
        "gol_fatti_squadra":8,
        "gol_subiti_squadra":9,
        "partite_giocate":1,
        "partite_vinte":0,
        "partite_pareggiate":0,
        "partite_perse":1,
        "voto_pagella":7.5,
        "id_partita":14,
        "squadra":"Chiari"
    },
    {
        "id_giocatore":134,
        "nome":"Max Botta",
        "gol_individuali":0,
        "gol_fatti_squadra":8,
        "gol_subiti_squadra":9,
        "partite_giocate":1,
        "partite_vinte":0,
        "partite_pareggiate":0,
        "partite_perse":1,
        "voto_pagella":6.25,
        "id_partita":14,
        "squadra":"Chiari"
    },
    {
        "id_giocatore":135,
        "nome":"Luca Peveraro",
        "gol_individuali":2,
        "gol_fatti_squadra":8,
        "gol_subiti_squadra":9,
        "partite_giocate":1,
        "partite_vinte":0,
        "partite_pareggiate":0,
        "partite_perse":1,
        "voto_pagella":6.5,
        "id_partita":14,
        "squadra":"Chiari"
    },
    {
        "id_giocatore":136,
        "nome":"Andrea Troletti",
        "gol_individuali":1,
        "gol_fatti_squadra":8,
        "gol_subiti_squadra":9,
        "partite_giocate":1,
        "partite_vinte":0,
        "partite_pareggiate":0,
        "partite_perse":1,
        "voto_pagella":5.5,
        "id_partita":14,
        "squadra":"Chiari"
    },
    {
        "id_giocatore":137,
        "nome":"Nicolas Carboni",
        "gol_individuali":1,
        "gol_fatti_squadra":8,
        "gol_subiti_squadra":9,
        "partite_giocate":1,
        "partite_vinte":0,
        "partite_pareggiate":0,
        "partite_perse":1,
        "voto_pagella":6.0,
        "id_partita":14,
        "squadra":"Chiari"
    },
    {
        "id_giocatore":138,
        "nome":"Nicol\u00f2 Berta",
        "gol_individuali":2,
        "gol_fatti_squadra":9,
        "gol_subiti_squadra":8,
        "partite_giocate":1,
        "partite_vinte":1,
        "partite_pareggiate":0,
        "partite_perse":0,
        "voto_pagella":6.5,
        "id_partita":14,
        "squadra":"Scuri"
    },
    {
        "id_giocatore":139,
        "nome":"Nosenzo Junior",
        "gol_individuali":0,
        "gol_fatti_squadra":9,
        "gol_subiti_squadra":8,
        "partite_giocate":1,
        "partite_vinte":1,
        "partite_pareggiate":0,
        "partite_perse":0,
        "voto_pagella":5.5,
        "id_partita":14,
        "squadra":"Scuri"
    },
    {
        "id_giocatore":140,
        "nome":"Matteo Nardone",
        "gol_individuali":1,
        "gol_fatti_squadra":9,
        "gol_subiti_squadra":8,
        "partite_giocate":1,
        "partite_vinte":1,
        "partite_pareggiate":0,
        "partite_perse":0,
        "voto_pagella":6.5,
        "id_partita":14,
        "squadra":"Scuri"
    },
    {
        "id_giocatore":141,
        "nome":"Luca Calce",
        "gol_individuali":1,
        "gol_fatti_squadra":9,
        "gol_subiti_squadra":8,
        "partite_giocate":1,
        "partite_vinte":1,
        "partite_pareggiate":0,
        "partite_perse":0,
        "voto_pagella":6.5,
        "id_partita":14,
        "squadra":"Scuri"
    },
    {
        "id_giocatore":142,
        "nome":"Davide Selva",
        "gol_individuali":5,
        "gol_fatti_squadra":9,
        "gol_subiti_squadra":8,
        "partite_giocate":1,
        "partite_vinte":1,
        "partite_pareggiate":0,
        "partite_perse":0,
        "voto_pagella":7.5,
        "id_partita":14,
        "squadra":"Scuri"
    }
]